yanga/__init__.py
yanga/__run.py
yanga/__run_cmd.py
yanga/cmake/__init__.py
yanga/cmake/artifacts_locator.py
yanga/cmake/builder.py
yanga/cmake/cmake_backend.py
yanga/cmake/coverage.py
yanga/cmake/cppcheck.py
yanga/cmake/create_executable.py
yanga/cmake/generator.py
yanga/cmake/gtest.py
yanga/cmake/objects_deps.py
yanga/cmake/reports.py
yanga/cmake/runner.py
yanga/cmake/targets_data.py
yanga/cmake/variant_config.py
yanga/commands/__init__.py
yanga/commands/__main__.py
yanga/commands/base.py
yanga/commands/cppcheck_report.py
yanga/commands/filter_compile_commands.py
yanga/commands/fix_html_links.py
yanga/commands/gcovr.py
yanga/commands/report_config.py
yanga/commands/run.py
yanga/commands/targets.py
yanga/docs/__init__.py
yanga/docs/sphinx.py
yanga/domain/__init__.py
yanga/domain/artifacts.py
yanga/domain/component_analyzer.py
yanga/domain/components.py
yanga/domain/config.py
yanga/domain/config_slurper.py
yanga/domain/execution_context.py
yanga/domain/project_slurper.py
yanga/domain/reports.py
yanga/domain/targets.py
yanga/gui/__init__.py
yanga/gui/icons.py
yanga/gui/resources/yanga.ico
yanga/gui/resources/yanga.png
yanga/gui/ygui.py
yanga/ini.py
yanga/kickstart/__init__.py
yanga/kickstart/create.py
yanga/kickstart/templates/common/.gitignore
yanga/kickstart/templates/common/CMakeLists.txt
yanga/kickstart/templates/common/bootstrap.json
yanga/kickstart/templates/common/build.ps1
yanga/kickstart/templates/common/conf.py
yanga/kickstart/templates/common/docs/components.md
yanga/kickstart/templates/common/index.md
yanga/kickstart/templates/common/platforms/windows/clang.cmake
yanga/kickstart/templates/common/platforms/windows/gcc.cmake
yanga/kickstart/templates/common/platforms/windows/yanga.yaml
yanga/kickstart/templates/common/pyproject.toml
yanga/kickstart/templates/common/scoopfile.json
yanga/kickstart/templates/common/yanga.ps1
yanga/kickstart/templates/common/yanga.yaml
yanga/kickstart/templates/mini/.vscode/cmake-kits.json
yanga-2.27.1.dist-info/METADATA
yanga-2.27.1.dist-info/WHEEL
yanga-2.27.1.dist-info/entry_points.txt
yanga-2.27.1.dist-info/licenses/LICENSE
yanga-2.27.1.dist-info/RECORD
