Metadata-Version: 2.4
Name: yanga
Version: 2.27.1
Summary: Yet another ninja generator to build C/CPP projects.
License: MIT
License-File: LICENSE
Author: cuinixam
Author-email: me@cuinixam.me
Requires-Python: <4.0,>=3.10
Classifier: Development Status :: 2 - Pre-Alpha
Classifier: Intended Audience :: Developers
Classifier: Natural Language :: English
Classifier: Operating System :: OS Independent
Classifier: Programming Language :: Python :: 3 :: Only
Classifier: Programming Language :: Python :: 3.10
Classifier: Programming Language :: Python :: 3.11
Classifier: Programming Language :: Python :: 3.12
Classifier: Programming Language :: Python :: 3.13
Classifier: Topic :: Software Development :: Libraries
Requires-Dist: clanguru (>=0.12,<1)
Requires-Dist: cookiecutter (>=2.1,<3)
Requires-Dist: customtkinter (>=5.2,<6)
Requires-Dist: gcovr (>=8.3,<9)
Requires-Dist: kspl (>=1,<2)
Requires-Dist: loguru (>=0.7,<1)
Requires-Dist: mashumaro (>=3.5,<4)
Requires-Dist: myst-parser (>=4,<5)
Requires-Dist: pick (>=2.2,<3)
Requires-Dist: pillow (>=10.1,<11)
Requires-Dist: py-app-dev (>=2.14,<3)
Requires-Dist: pypeline-runner (>=1,<2)
Requires-Dist: typer (>=0.12,<1)
Project-URL: Bug Tracker, https://github.com/cuinixam/yanga/issues
Project-URL: Changelog, https://github.com/cuinixam/yanga/blob/main/CHANGELOG.md
Project-URL: Documentation, https://yanga.readthedocs.io
Project-URL: Repository, https://github.com/cuinixam/yanga
